README.md
setup.py
visionToolkit/__init__.py
visionToolkit.egg-info/PKG-INFO
visionToolkit.egg-info/SOURCES.txt
visionToolkit.egg-info/dependency_links.txt
visionToolkit.egg-info/requires.txt
visionToolkit.egg-info/top_level.txt
visionToolkit/aoi_based_analysis/__init__.py
visionToolkit/aoi_based_analysis/aoi_based_processing.py
visionToolkit/aoi_based_analysis/gaze_transition_entropy.py
visionToolkit/aoi_based_analysis/lempei_ziv_complexity.py
visionToolkit/aoi_based_analysis/n_gram.py
visionToolkit/basic_analysis/__init__.py
visionToolkit/basic_analysis/angular_coord.py
visionToolkit/basic_analysis/basic_processing.py
visionToolkit/basic_analysis/scan_path.py
visionToolkit/basic_analysis/smoothing.py
visionToolkit/physiological_analysis/__init__.py
visionToolkit/physiological_analysis/fixations.py
visionToolkit/physiological_analysis/microsaccades.py
visionToolkit/physiological_analysis/physiological_processing.py
visionToolkit/physiological_analysis/saccades.py
visionToolkit/scan_path_analysis/__init__.py
visionToolkit/scan_path_analysis/multi_match.py
visionToolkit/scan_path_analysis/scan_match.py
visionToolkit/scan_path_analysis/scan_path_processing.py
visionToolkit/statistical_analysis/__init__.py
visionToolkit/statistical_analysis/dynamic_variables/__init__.py
visionToolkit/statistical_analysis/dynamic_variables/dynamic_processing.py
visionToolkit/statistical_analysis/dynamic_variables/fractal_dimension.py
visionToolkit/statistical_analysis/dynamic_variables/length_over_area.py
visionToolkit/statistical_analysis/dynamic_variables/mean_frequency.py
visionToolkit/statistical_analysis/dynamic_variables/phase_plane.py
visionToolkit/statistical_analysis/dynamic_variables/sway_area_ps.py
visionToolkit/statistical_analysis/dynamic_variables/sway_density.py
visionToolkit/statistical_analysis/dynamic_variables/velocity.py
visionToolkit/statistical_analysis/frequency_variables/__init__.py
visionToolkit/statistical_analysis/frequency_variables/frequency_processing.py
visionToolkit/statistical_analysis/frequency_variables/welch_periodogram.py
visionToolkit/statistical_analysis/positional_variables/__init__.py
