Metadata-Version: 2.1
Name: visionToolkit
Version: 0.1.11
Summary: Gaze Analysis Library
Home-page: UNKNOWN
Author: Laborde Perochon Roques
License: ENS_Paris_Saclay
Platform: UNKNOWN
